mecheye/__init__.py
mecheye/_area_scan_3d_camera.so
mecheye/_profiler.so
mecheye/_shared.so
mecheye/area_scan_3d_camera.py
mecheye/area_scan_3d_camera_utils.py
mecheye/libMechEyeApi.so
mecheye/profiler.py
mecheye/profiler_utils.py
mecheye/shared.py
mecheyeapi-2.5.4.dist-info/LICENSE
mecheyeapi-2.5.4.dist-info/METADATA
mecheyeapi-2.5.4.dist-info/WHEEL
mecheyeapi-2.5.4.dist-info/top_level.txt
mecheyeapi-2.5.4.dist-info/RECORD
