Metadata-Version: 2.4
Name: MechEyeAPI
Version: 2.5.4
Summary: Mech-Eye Industrial 3D Camera API
Author: Mech-Mind Robotics Technologies
License: BSD 3-Clause License
Project-URL: Homepage, https://www.mech-mind.com
Classifier: License :: OSI Approved :: BSD License
Classifier: Programming Language :: Python :: 3
Classifier: Programming Language :: Python :: Implementation :: CPython
Classifier: Topic :: Scientific/Engineering
Classifier: Operating System :: OS Independent
License-File: LICENSE
Requires-Dist: numpy
Dynamic: license-file
